structr/__init__.py
structr/structr.py
structr-0.1.dist-info/LICENSE
structr-0.1.dist-info/METADATA
structr-0.1.dist-info/WHEEL
structr-0.1.dist-info/top_level.txt
structr-0.1.dist-info/RECORD
